nemreport/__init__.py
nemreport/__main__.py
nemreport/cli.py
nemreport/model.py
nemreport/prepare_db.py
nemreport/report.py
nemreport/version.py
nemreport/templates/bootstrap.min.css
nemreport/templates/index.html
nemreport/templates/nmi-report.html
nemreport-0.0.3.dist-info/entry_points.txt
nemreport-0.0.3.dist-info/LICENSE
nemreport-0.0.3.dist-info/WHEEL
nemreport-0.0.3.dist-info/METADATA
nemreport-0.0.3.dist-info/RECORD
