Metadata-Version: 2.1
Name: nemreport
Version: 0.0.3
Summary: Generate energy report from NEM meter data files
Keywords: energy,NEM12,NEM13
Author-email: Alex Guinman <alex@guinman.id.au>
Requires-Python: >=3.8
Classifier: License :: OSI Approved :: MIT License
Classifier: Programming Language :: Python :: 3
Classifier: Programming Language :: Python :: 3.11
Classifier: Programming Language :: Python :: 3.10
Classifier: Programming Language :: Python :: 3.9
Classifier: Programming Language :: Python :: 3.8
Classifier: Operating System :: OS Independent
Requires-Dist: nemreader>=0.8.7
Requires-Dist: jinja2
Requires-Dist: pandas
Requires-Dist: plotly
Requires-Dist: calplot
Requires-Dist: sqlite_utils
Requires-Dist: pydantic
Requires-Dist: typer
Requires-Dist: black ; extra == "dev"
Requires-Dist: flake8 ; extra == "dev"
Requires-Dist: flake8-bugbear ; extra == "dev"
Requires-Dist: pep8-naming ; extra == "dev"
Requires-Dist: flake8-builtins ; extra == "dev"
Requires-Dist: pytest >=2.7.3 ; extra == "test"
Requires-Dist: pytest-cov ; extra == "test"
Requires-Dist: mypy ; extra == "test"
Project-URL: Source, https://github.com/aguinane/energy-report
Provides-Extra: dev
Provides-Extra: test
